{
    "word": "brauche",
    "gender": "f",
    "article": "die",
    "word_type": "verb",
    "infinitive": "brauchen",
    "translation": "need",
    "example_sentences": [
        {
            "de": "Ich brauche deine Hilfe.",
            "en": "I need your help."
        },
        {
            "de": "Brauchst du etwas?",
            "en": "Do you need anything?"
        }
    ],
    "usage_frequency": 8,
    "ipa": "ˈbʁaʊ̯çə",
    "verb_auxiliary": "haben",
    "difficulty_level": "A2",
    "irregular": true,
    "present_3rd_singular": "braucht",
    "past_perfect": "hat gebraucht",
    "preterite": "brauchte",
    "frequency_scale": 9
}