{
    "word": "entsetzen",
    "gender": "neuter",
    "article": "das",
    "word_type": "noun",
    "translation": "dismay",
    "example_sentences": [
        {
            "de": "Das Entsetzen stand ihm ins Gesicht geschrieben.",
            "en": "Dismay was written all over his face."
        },
        {
            "de": "Ich konnte mein Entsetzen nicht verbergen.",
            "en": "I couldn't hide my dismay."
        }
    ],
    "usage_frequency": 7,
    "ipa": "/ɛntˈzɛtsən/",
    "verb_auxiliary": null,
    "difficulty_level": "B1",
    "irregular": false,
    "present_3rd_singular": null,
    "past_perfect": null,
    "preterite": null,
    "frequency_scale": 8
}