{
    "word": "versuch",
    "gender": "m",
    "article": "der",
    "word_type": "noun",
    "translation": "attempt",
    "example_sentences": [
        {
            "de": "Ich werde einen Versuch machen.",
            "en": "I will make an attempt."
        },
        {
            "de": "Sein Versuch war erfolglos.",
            "en": "His attempt was unsuccessful."
        }
    ],
    "usage_frequency": 7,
    "ipa": "/fɛɐ̯ˈzʊx/",
    "verb_auxiliary": null,
    "difficulty_level": "B1",
    "irregular": false,
    "present_3s": null,
    "past_perfect": null,
    "preterite": null,
    "frequency_scale": 7
}