{
    "word": "anzunehmen",
    "gender": "neuter",
    "article": "das",
    "word_type": "verb",
    "infinitive": "annehmen",
    "translation": "to assume",
    "example_sentences": [
        {
            "de": "Es ist anzunehmen, dass er bald zurückkommt.",
            "en": "It is to be assumed that he will come back soon."
        },
        {
            "de": "Ich nehme an, dass du Recht hast.",
            "en": "I assume that you are right."
        }
    ],
    "usage_frequency": 7,
    "ipa": "/ˈan.zuˌneː.mən/",
    "verb_auxiliary": "haben",
    "difficulty_level": "B1",
    "irregular": true,
    "present_3rd_singular": "nimmt an",
    "past_perfect": "hat angenommen",
    "preterite": "nahm an",
    "frequency_scale": 8
}