{
    "word": "ihren",
    "gender": "f",
    "article": "die",
    "word_type": "Pronoun",
    "translation": "their",
    "example_sentences": [
        {
            "de": "Ich habe ihren Hund gesehen.",
            "en": "I saw their dog."
        },
        {
            "de": "Ihre Kinder sind sehr nett.",
            "en": "Their children are very nice."
        }
    ],
    "usage_frequency": 8,
    "ipa": "ˈiːʁən",
    "verb_auxiliary": null,
    "difficulty_level": "A1",
    "irregular": false,
    "present_3s": null,
    "past_perfect": null,
    "preterite": null,
    "frequency_scale": 7
}