{
    "word": "indischen",
    "gender": "neuter",
    "article": "das",
    "word_type": "adjective",
    "translation": "Indian",
    "example_sentences": [
        {
            "de": "Ich esse gerne indisches Essen.",
            "en": "I like to eat Indian food."
        },
        {
            "de": "Die indische Küche ist sehr vielfältig.",
            "en": "Indian cuisine is very diverse."
        }
    ],
    "usage_frequency": 7,
    "ipa": "ɪnˈdɪʃən",
    "verb_auxiliary": null,
    "difficulty_level": "B1",
    "irregular": false,
    "present_3rd_singular": null,
    "past_perfect": null,
    "preterite": null,
    "frequency_scale": 7
}