{
    "word": "lässt",
    "gender": "m",
    "article": "der",
    "word_type": "lassen",
    "translation": "lets",
    "example_sentences": [
        {
            "de": "Er lässt den Ball fallen.",
            "en": "He lets the ball drop."
        },
        {
            "de": "Sie lässt ihn nicht allein.",
            "en": "She doesn't leave him alone."
        }
    ],
    "usage_frequency": 8,
    "ipa_code": "/lɛst/",
    "verb_auxiliary": "hat",
    "difficulty_level": "B1",
    "irregular": true,
    "present_3rd_form_singular": "lässt",
    "past_perfect": "gelassen",
    "preterite": "ließ",
    "frequency_scale": 7
}